ExpertOptionAPI/__init__.py
ExpertOptionAPI/expert.py
ExpertOptionAPI/indicators.py
ExpertOptionAPI/_exceptions/__init__.py
ExpertOptionAPI/_exceptions/Buying/BuyExceptions.py
ExpertOptionAPI/_exceptions/Buying/__init__.py
ExpertOptionAPI/api/__init__.py
ExpertOptionAPI/api/constants.py
ExpertOptionAPI/api/global_values.py
ExpertOptionAPI/api/backend/__init__.py
ExpertOptionAPI/api/backend/client.py
ExpertOptionAPI/api/backend/server.py
ExpertOptionAPI/api/backend/ws/__init__.py
ExpertOptionAPI/api/backend/ws/profile.py
ExpertOptionAPI/api/backend/ws/channels/__init__.py
ExpertOptionAPI/api/backend/ws/channels/base.py
ExpertOptionAPI/api/backend/ws/channels/ping.py
ExpertOptionAPI/api/prebuild/__init__.py
ExpertOptionAPI/api/prebuild/bot/__init__.py
ExpertOptionAPI/api/prebuild/bot/aligator.py
ExpertOptionAPI/api/prebuild/bot/rsi.py
ExpertOptionAPI-0.8.dist-info/LICENSE
ExpertOptionAPI-0.8.dist-info/METADATA
ExpertOptionAPI-0.8.dist-info/WHEEL
ExpertOptionAPI-0.8.dist-info/top_level.txt
ExpertOptionAPI-0.8.dist-info/RECORD
