Metadata-Version: 2.1
Name: ExpertOptionAPI
Version: 0.8
License-File: LICENSE
Requires-Dist: websocket
Requires-Dist: simplejson
Requires-Dist: pandas
Requires-Dist: pause
Requires-Dist: websocket-client
